topsis/__init__.py
topsis/topsis.py
Topsis_Ruhani_102203833-0.1.dist-info/METADATA
Topsis_Ruhani_102203833-0.1.dist-info/WHEEL
Topsis_Ruhani_102203833-0.1.dist-info/entry_points.txt
Topsis_Ruhani_102203833-0.1.dist-info/top_level.txt
Topsis_Ruhani_102203833-0.1.dist-info/RECORD
