Metadata-Version: 2.1
Name: Topsis-Ruhani-102203833
Version: 0.1
Summary: TOPSIS algorithm implementation
Home-page: https://github.com/Ruhani2703/Topsis
Author: Ruhani Arora
License: UNKNOWN
Platform: UNKNOWN
Classifier: Programming Language :: Python :: 3
Classifier: License :: OSI Approved :: MIT License
Requires-Dist: pandas
Requires-Dist: numpy
